{
  "$schema": "../node_modules/@tauri-apps/cli/config.schema.json",
  "productName": "ai-knowledge-extractor",
  "version": "0.1.0",
  "identifier": "com.aiknowledge.extractor",
  "build": {
    "frontendDist": "../build",
    "devUrl": "http://localhost:3000",
    "beforeDevCommand": "npm run dev",
    "beforeBuildCommand": "npm run build"
  },
  "app": {
    "windows": [
      {
        "title": "AI知识提取器",
        "width": 1024,
        "height": 768,
        "resizable": true,
        "fullscreen": false,
        "center": true
      }
    ],
    "security": {
      "csp": null
    }
  },
  "bundle": {
    "active": true,
    "targets": ["msi", "nsis"],
    "icon": [
      "icons/32x32.png",
      "icons/128x128.png",
      "icons/128x128@2x.png",
      "icons/icon.icns",
      "icons/icon.ico"
    ],
    "windows": {
      "certificateThumbprint": null,
      "digestAlgorithm": "sha256",
      "timestampUrl": "",
      "wix": {
        "language": ["zh-CN"],
        "template": null
      },
      "nsis": {
        "languages": ["SimpChinese"],
        "installMode": "currentUser",
        "displayLanguageSelector": true
      }
    }
  }
}
